[
  {"id": 1, "chinese": "你好", "pinyin": "nǐ hǎo", "portuguese": "olá", "categorias": ["cumprimento"]},
  {"id": 2, "chinese": "谢谢", "pinyin": "xiè xiè", "portuguese": "obrigado", "categorias": ["expressão"]},
  {"id": 3, "chinese": "再见", "pinyin": "zài jiàn", "portuguese": "tchau", "categorias": ["cumprimento"]},
  {"id": 4, "chinese": "对不起", "pinyin": "duì bu qǐ", "portuguese": "desculpa", "categorias": ["expressão"]},
  {"id": 5, "chinese": "水", "pinyin": "shuǐ", "portuguese": "água", "categorias": ["bebida"]},
  {"id": 6, "chinese": "茶", "pinyin": "chá", "portuguese": "chá", "categorias": ["bebida"]},
  {"id": 7, "chinese": "咖啡", "pinyin": "kā fēi", "portuguese": "café", "categorias": ["bebida"]},
  {"id": 8, "chinese": "牛奶", "pinyin": "niú nǎi", "portuguese": "leite", "categorias": ["bebida"]},
  {"id": 9, "chinese": "猫", "pinyin": "māo", "portuguese": "gato", "categorias": ["animal"]},
  {"id": 10, "chinese": "狗", "pinyin": "gǒu", "portuguese": "cachorro", "categorias": ["animal"]},
  {"id": 11, "chinese": "鸟", "pinyin": "niǎo", "portuguese": "pássaro", "categorias": ["animal"]},
  {"id": 12, "chinese": "鱼", "pinyin": "yú", "portuguese": "peixe", "categorias": ["animal"]},
  {"id": 13, "chinese": "吃", "pinyin": "chī", "portuguese": "comer", "categorias": ["verbo"]},
  {"id": 14, "chinese": "喝", "pinyin": "hē", "portuguese": "beber", "categorias": ["verbo"]},
  {"id": 15, "chinese": "看", "pinyin": "kàn", "portuguese": "ver/olhar", "categorias": ["verbo"]},
  {"id": 16, "chinese": "去", "pinyin": "qù", "portuguese": "ir", "categorias": ["verbo"]},
  {"id": 17, "chinese": "大", "pinyin": "dà", "portuguese": "grande", "categorias": ["adjetivo"]},
  {"id": 18, "chinese": "小", "pinyin": "xiǎo", "portuguese": "pequeno", "categorias": ["adjetivo"]},
  {"id": 19, "chinese": "好", "pinyin": "hǎo", "portuguese": "bom", "categorias": ["adjetivo"]},
  {"id": 20, "chinese": "热", "pinyin": "rè", "portuguese": "quente", "categorias": ["adjetivo"]},
  {"id": 21, "chinese": "妈妈", "pinyin": "mā ma", "portuguese": "mãe", "categorias": ["família"]},
  {"id": 22, "chinese": "爸爸", "pinyin": "bà ba", "portuguese": "pai", "categorias": ["família"]},
  {"id": 23, "chinese": "哥哥", "pinyin": "gē ge", "portuguese": "irmão mais velho", "categorias": ["família"]},
  {"id": 24, "chinese": "姐姐", "pinyin": "jiě jie", "portuguese": "irmã mais velha", "categorias": ["família"]},
  {"id": 25, "chinese": "弟弟", "pinyin": "dì di", "portuguese": "irmão mais novo", "categorias": ["família"]},
  {"id": 26, "chinese": "妹妹", "pinyin": "mèi mei", "portuguese": "irmã mais nova", "categorias": ["família"]},
  {"id": 27, "chinese": "米饭", "pinyin": "mǐ fàn", "portuguese": "arroz", "categorias": ["comida"]},
  {"id": 28, "chinese": "面条", "pinyin": "miàn tiáo", "portuguese": "macarrão", "categorias": ["comida"]},
  {"id": 29, "chinese": "面包", "pinyin": "miàn bāo", "portuguese": "pão", "categorias": ["comida"]},
  {"id": 30, "chinese": "鸡蛋", "pinyin": "jī dàn", "portuguese": "ovo", "categorias": ["comida"]},
  {"id": 31, "chinese": "书", "pinyin": "shū", "portuguese": "livro", "categorias": ["substantivo", "objeto"]},
  {"id": 32, "chinese": "桌子", "pinyin": "zhuō zi", "portuguese": "mesa", "categorias": ["substantivo", "objeto"]},
  {"id": 33, "chinese": "椅子", "pinyin": "yǐ zi", "portuguese": "cadeira", "categorias": ["substantivo", "objeto"]},
  {"id": 34, "chinese": "电脑", "pinyin": "diàn nǎo", "portuguese": "computador", "categorias": ["substantivo", "objeto"]},
  {"id": 35, "chinese": "我", "pinyin": "wǒ", "portuguese": "eu", "categorias": ["pronome"]},
  {"id": 36, "chinese": "你", "pinyin": "nǐ", "portuguese": "você", "categorias": ["pronome"]},
  {"id": 37, "chinese": "他", "pinyin": "tā", "portuguese": "ele", "categorias": ["pronome"]},
  {"id": 38, "chinese": "她", "pinyin": "tā", "portuguese": "ela", "categorias": ["pronome"]},
  {"id": 39, "chinese": "在", "pinyin": "zài", "portuguese": "em / estar", "categorias": ["preposição", "verbo"]},
  {"id": 40, "chinese": "早上好", "pinyin": "zǎo shang hǎo", "portuguese": "bom dia", "categorias": ["cumprimento"]},
  {"id": 41, "chinese": "晚上好", "pinyin": "wǎn shang hǎo", "portuguese": "boa noite", "categorias": ["cumprimento"]},
  {"id": 42, "chinese": "请", "pinyin": "qǐng", "portuguese": "por favor", "categorias": ["expressão"]},
  {"id": 43, "chinese": "不客气", "pinyin": "bú kè qi", "portuguese": "de nada", "categorias": ["expressão"]},
  {"id": 44, "chinese": "没关系", "pinyin": "méi guān xi", "portuguese": "não importa", "categorias": ["expressão"]},
  {"id": 45, "chinese": "啤酒", "pinyin": "pí jiǔ", "portuguese": "cerveja", "categorias": ["bebida"]},
  {"id": 46, "chinese": "果汁", "pinyin": "guǒ zhī", "portuguese": "suco", "categorias": ["bebida"]},
  {"id": 47, "chinese": "可乐", "pinyin": "kě lè", "portuguese": "refrigerante", "categorias": ["bebida"]},
  {"id": 48, "chinese": "马", "pinyin": "mǎ", "portuguese": "cavalo", "categorias": ["animal"]},
  {"id": 49, "chinese": "猪", "pinyin": "zhū", "portuguese": "porco", "categorias": ["animal"]},
  {"id": 50, "chinese": "牛", "pinyin": "niú", "portuguese": "vaca/boi", "categorias": ["animal"]},
  {"id": 51, "chinese": "羊", "pinyin": "yáng", "portuguese": "ovelha/cabra", "categorias": ["animal"]},
  {"id": 52, "chinese": "鸡", "pinyin": "jī", "portuguese": "galinha", "categorias": ["animal"]},
  {"id": 53, "chinese": "兔子", "pinyin": "tù zi", "portuguese": "coelho", "categorias": ["animal"]},
  {"id": 54, "chinese": "老虎", "pinyin": "lǎo hǔ", "portuguese": "tigre", "categorias": ["animal"]},
  {"id": 55, "chinese": "说", "pinyin": "shuō", "portuguese": "falar/dizer", "categorias": ["verbo"]},
  {"id": 56, "chinese": "听", "pinyin": "tīng", "portuguese": "ouvir", "categorias": ["verbo"]},
  {"id": 57, "chinese": "写", "pinyin": "xiě", "portuguese": "escrever", "categorias": ["verbo"]},
  {"id": 58, "chinese": "读", "pinyin": "dú", "portuguese": "ler", "categorias": ["verbo"]},
  {"id": 59, "chinese": "走", "pinyin": "zǒu", "portuguese": "andar", "categorias": ["verbo"]},
  {"id": 60, "chinese": "跑", "pinyin": "pǎo", "portuguese": "correr", "categorias": ["verbo"]},
  {"id": 61, "chinese": "坐", "pinyin": "zuò", "portuguese": "sentar", "categorias": ["verbo"]},
  {"id": 62, "chinese": "站", "pinyin": "zhàn", "portuguese": "ficar em pé", "categorias": ["verbo"]},
  {"id": 63, "chinese": "睡", "pinyin": "shuì", "portuguese": "dormir", "categorias": ["verbo"]},
  {"id": 64, "chinese": "醒", "pinyin": "xǐng", "portuguese": "acordar", "categorias": ["verbo"]},
  {"id": 65, "chinese": "买", "pinyin": "mǎi", "portuguese": "comprar", "categorias": ["verbo"]},
  {"id": 66, "chinese": "卖", "pinyin": "mài", "portuguese": "vender", "categorias": ["verbo"]},
  {"id": 67, "chinese": "给", "pinyin": "gěi", "portuguese": "dar", "categorias": ["verbo"]},
  {"id": 68, "chinese": "冷", "pinyin": "lěng", "portuguese": "frio", "categorias": ["adjetivo"]},
  {"id": 69, "chinese": "新", "pinyin": "xīn", "portuguese": "novo", "categorias": ["adjetivo"]},
  {"id": 70, "chinese": "旧", "pinyin": "jiù", "portuguese": "velho/usado", "categorias": ["adjetivo"]},
  {"id": 71, "chinese": "快", "pinyin": "kuài", "portuguese": "rápido", "categorias": ["adjetivo"]},
  {"id": 72, "chinese": "慢", "pinyin": "màn", "portuguese": "lento", "categorias": ["adjetivo"]},
  {"id": 73, "chinese": "高", "pinyin": "gāo", "portuguese": "alto", "categorias": ["adjetivo"]},
  {"id": 74, "chinese": "矮", "pinyin": "ǎi", "portuguese": "baixo", "categorias": ["adjetivo"]},
  {"id": 75, "chinese": "漂亮", "pinyin": "piào liang", "portuguese": "bonito", "categorias": ["adjetivo"]},
  {"id": 76, "chinese": "丑", "pinyin": "chǒu", "portuguese": "feio", "categorias": ["adjetivo"]},
  {"id": 77, "chinese": "胖", "pinyin": "pàng", "portuguese": "gordo", "categorias": ["adjetivo"]},
  {"id": 78, "chinese": "瘦", "pinyin": "shòu", "portuguese": "magro", "categorias": ["adjetivo"]},
  {"id": 79, "chinese": "爷爷", "pinyin": "yé ye", "portuguese": "avô paterno", "categorias": ["família"]},
  {"id": 80, "chinese": "奶奶", "pinyin": "nǎi nai", "portuguese": "avó paterna", "categorias": ["família"]},
  {"id": 81, "chinese": "外公", "pinyin": "wài gōng", "portuguese": "avô materno", "categorias": ["família"]},
  {"id": 82, "chinese": "外婆", "pinyin": "wài pó", "portuguese": "avó materna", "categorias": ["família"]},
  {"id": 83, "chinese": "儿子", "pinyin": "ér zi", "portuguese": "filho", "categorias": ["família"]},
  {"id": 84, "chinese": "女儿", "pinyin": "nǚ ér", "portuguese": "filha", "categorias": ["família"]},
  {"id": 85, "chinese": "丈夫", "pinyin": "zhàng fu", "portuguese": "marido", "categorias": ["família"]},
  {"id": 86, "chinese": "妻子", "pinyin": "qī zi", "portuguese": "esposa", "categorias": ["família"]},
  {"id": 87, "chinese": "饺子", "pinyin": "jiǎo zi", "portuguese": "pastel chinês", "categorias": ["comida"]},
  {"id": 88, "chinese": "火锅", "pinyin": "huǒ guō", "portuguese": "fondue chinês", "categorias": ["comida"]},
  {"id": 89, "chinese": "豆腐", "pinyin": "dòu fu", "portuguese": "tofu", "categorias": ["comida"]},
  {"id": 90, "chinese": "水果", "pinyin": "shuǐ guǒ", "portuguese": "fruta", "categorias": ["comida"]},
  {"id": 91, "chinese": "苹果", "pinyin": "píng guǒ", "portuguese": "maçã", "categorias": ["comida"]},
  {"id": 92, "chinese": "香蕉", "pinyin": "xiāng jiāo", "portuguese": "banana", "categorias": ["comida"]},
  {"id": 93, "chinese": "西瓜", "pinyin": "xī guā", "portuguese": "melancia", "categorias": ["comida"]},
  {"id": 94, "chinese": "葡萄", "pinyin": "pú tao", "portuguese": "uva", "categorias": ["comida"]},
  {"id": 95, "chinese": "橙子", "pinyin": "chéng zi", "portuguese": "laranja", "categorias": ["comida"]},
  {"id": 96, "chinese": "门", "pinyin": "mén", "portuguese": "porta", "categorias": ["substantivo", "objeto"]},
  {"id": 97, "chinese": "窗户", "pinyin": "chuāng hu", "portuguese": "janela", "categorias": ["substantivo", "objeto"]},
  {"id": 98, "chinese": "床", "pinyin": "chuáng", "portuguese": "cama", "categorias": ["substantivo", "objeto"]},
  {"id": 99, "chinese": "灯", "pinyin": "dēng", "portuguese": "lâmpada/luz", "categorias": ["substantivo", "objeto"]},
  {"id": 100, "chinese": "电话", "pinyin": "diàn huà", "portuguese": "telefone", "categorias": ["substantivo", "objeto"]},
  {"id": 101, "chinese": "手机", "pinyin": "shǒu jī", "portuguese": "celular", "categorias": ["substantivo", "objeto"]},
  {"id": 102, "chinese": "电视", "pinyin": "diàn shì", "portuguese": "televisão", "categorias": ["substantivo", "objeto"]},
  {"id": 103, "chinese": "冰箱", "pinyin": "bīng xiāng", "portuguese": "geladeira", "categorias": ["substantivo", "objeto"]},
  {"id": 104, "chinese": "洗衣机", "pinyin": "xǐ yī jī", "portuguese": "máquina de lavar", "categorias": ["substantivo", "objeto"]},
  {"id": 105, "chinese": "空调", "pinyin": "kōng tiáo", "portuguese": "ar condicionado", "categorias": ["substantivo", "objeto"]},
  {"id": 106, "chinese": "我们", "pinyin": "wǒ men", "portuguese": "nós", "categorias": ["pronome"]},
  {"id": 107, "chinese": "你们", "pinyin": "nǐ men", "portuguese": "vocês", "categorias": ["pronome"]},
  {"id": 108, "chinese": "他们", "pinyin": "tā men", "portuguese": "eles/elas", "categorias": ["pronome"]},
  {"id": 109, "chinese": "这", "pinyin": "zhè", "portuguese": "este/isto", "categorias": ["pronome"]},
  {"id": 110, "chinese": "那", "pinyin": "nà", "portuguese": "aquele/isso", "categorias": ["pronome"]},
  {"id": 111, "chinese": "谁", "pinyin": "shéi", "portuguese": "quem", "categorias": ["pronome"]},
  {"id": 112, "chinese": "什么", "pinyin": "shén me", "portuguese": "o que/qual", "categorias": ["pronome"]},
  {"id": 113, "chinese": "哪里", "pinyin": "nǎ lǐ", "portuguese": "onde", "categorias": ["pronome"]},
  {"id": 114, "chinese": "怎么", "pinyin": "zěn me", "portuguese": "como", "categorias": ["pronome"]},
  {"id": 115, "chinese": "和", "pinyin": "hé", "portuguese": "e/com", "categorias": ["preposição"]},
  {"id": 116, "chinese": "的", "pinyin": "de", "portuguese": "de (posse)", "categorias": ["preposição"]},
  {"id": 117, "chinese": "对", "pinyin": "duì", "portuguese": "para/correto", "categorias": ["preposição", "adjetivo"]},
  {"id": 118, "chinese": "从", "pinyin": "cóng", "portuguese": "de/desde", "categorias": ["preposição"]},
  {"id": 119, "chinese": "到", "pinyin": "dào", "portuguese": "para/até", "categorias": ["preposição"]},
  {"id": 120, "chinese": "里面", "pinyin": "lǐ miàn", "portuguese": "dentro", "categorias": ["preposição"]},
  {"id": 121, "chinese": "外面", "pinyin": "wài miàn", "portuguese": "fora", "categorias": ["preposição"]},
  {"id": 122, "chinese": "上面", "pinyin": "shàng miàn", "portuguese": "em cima", "categorias": ["preposição"]},
  {"id": 123, "chinese": "下面", "pinyin": "xià miàn", "portuguese": "embaixo", "categorias": ["preposição"]},
  {"id": 124, "chinese": "前面", "pinyin": "qián miàn", "portuguese": "na frente", "categorias": ["preposição"]},
  {"id": 125, "chinese": "后面", "pinyin": "hòu miàn", "portuguese": "atrás", "categorias": ["preposição"]},
  {"id": 126, "chinese": "今天", "pinyin": "jīn tiān", "portuguese": "hoje", "categorias": ["tempo"]},
  {"id": 127, "chinese": "明天", "pinyin": "míng tiān", "portuguese": "amanhã", "categorias": ["tempo"]},
  {"id": 128, "chinese": "昨天", "pinyin": "zuó tiān", "portuguese": "ontem", "categorias": ["tempo"]},
  {"id": 129, "chinese": "现在", "pinyin": "xiàn zài", "portuguese": "agora", "categorias": ["tempo"]},
  {"id": 130, "chinese": "早上", "pinyin": "zǎo shang", "portuguese": "manhã", "categorias": ["tempo"]},
  {"id": 131, "chinese": "中午", "pinyin": "zhōng wǔ", "portuguese": "meio-dia", "categorias": ["tempo"]},
  {"id": 132, "chinese": "晚上", "pinyin": "wǎn shang", "portuguese": "noite", "categorias": ["tempo"]},
  {"id": 133, "chinese": "星期", "pinyin": "xīng qī", "portuguese": "semana", "categorias": ["tempo"]},
  {"id": 134, "chinese": "月", "pinyin": "yuè", "portuguese": "mês/lua", "categorias": ["tempo"]},
  {"id": 135, "chinese": "年", "pinyin": "nián", "portuguese": "ano", "categorias": ["tempo"]},
  {"id": 136, "chinese": "红色", "pinyin": "hóng sè", "portuguese": "vermelho", "categorias": ["cor"]},
  {"id": 137, "chinese": "蓝色", "pinyin": "lán sè", "portuguese": "azul", "categorias": ["cor"]},
  {"id": 138, "chinese": "绿色", "pinyin": "lǜ sè", "portuguese": "verde", "categorias": ["cor"]},
  {"id": 139, "chinese": "黄色", "pinyin": "huáng sè", "portuguese": "amarelo", "categorias": ["cor"]},
  {"id": 140, "chinese": "白色", "pinyin": "bái sè", "portuguese": "branco", "categorias": ["cor"]},
  {"id": 141, "chinese": "黑色", "pinyin": "hēi sè", "portuguese": "preto", "categorias": ["cor"]},
  {"id": 142, "chinese": "一", "pinyin": "yī", "portuguese": "um", "categorias": ["número"]},
  {"id": 143, "chinese": "二", "pinyin": "èr", "portuguese": "dois", "categorias": ["número"]},
  {"id": 144, "chinese": "三", "pinyin": "sān", "portuguese": "três", "categorias": ["número"]},
  {"id": 145, "chinese": "四", "pinyin": "sì", "portuguese": "quatro", "categorias": ["número"]},
  {"id": 146, "chinese": "五", "pinyin": "wǔ", "portuguese": "cinco", "categorias": ["número"]},
  {"id": 147, "chinese": "六", "pinyin": "liù", "portuguese": "seis", "categorias": ["número"]},
  {"id": 148, "chinese": "七", "pinyin": "qī", "portuguese": "sete", "categorias": ["número"]},
  {"id": 149, "chinese": "八", "pinyin": "bā", "portuguese": "oito", "categorias": ["número"]},
  {"id": 150, "chinese": "九", "pinyin": "jiǔ", "portuguese": "nove", "categorias": ["número"]},
  {"id": 151, "chinese": "十", "pinyin": "shí", "portuguese": "dez", "categorias": ["número"]},
  {"id": 152, "chinese": "学校", "pinyin": "xué xiào", "portuguese": "escola", "categorias": ["lugar"]},
  {"id": 153, "chinese": "医院", "pinyin": "yī yuàn", "portuguese": "hospital", "categorias": ["lugar"]},
  {"id": 154, "chinese": "商店", "pinyin": "shāng diàn", "portuguese": "loja", "categorias": ["lugar"]},
  {"id": 155, "chinese": "饭店", "pinyin": "fàn diàn", "portuguese": "restaurante", "categorias": ["lugar"]},
  {"id": 156, "chinese": "银行", "pinyin": "yín háng", "portuguese": "banco", "categorias": ["lugar"]},
  {"id": 157, "chinese": "公园", "pinyin": "gōng yuán", "portuguese": "parque", "categorias": ["lugar"]},
  {"id": 158, "chinese": "超市", "pinyin": "chāo shì", "portuguese": "supermercado", "categorias": ["lugar"]},
  {"id": 159, "chinese": "机场", "pinyin": "jī chǎng", "portuguese": "aeroporto", "categorias": ["lugar"]},
  {"id": 160, "chinese": "车站", "pinyin": "chē zhàn", "portuguese": "estação", "categorias": ["lugar"]},
  {"id": 161, "chinese": "家", "pinyin": "jiā", "portuguese": "casa/família", "categorias": ["lugar", "família"]},
  {"id": 162, "chinese": "工作", "pinyin": "gōng zuò", "portuguese": "trabalho/trabalhar", "categorias": ["verbo", "substantivo"]},
  {"id": 163, "chinese": "学习", "pinyin": "xué xí", "portuguese": "estudar", "categorias": ["verbo"]},
  {"id": 164, "chinese": "喜欢", "pinyin": "xǐ huān", "portuguese": "gostar", "categorias": ["verbo"]},
  {"id": 165, "chinese": "爱", "pinyin": "ài", "portuguese": "amar", "categorias": ["verbo"]},
  {"id": 166, "chinese": "想", "pinyin": "xiǎng", "portuguese": "pensar/querer", "categorias": ["verbo"]},
  {"id": 167, "chinese": "知道", "pinyin": "zhī dào", "portuguese": "saber", "categorias": ["verbo"]},
  {"id": 168, "chinese": "认识", "pinyin": "rèn shi", "portuguese": "conhecer", "categorias": ["verbo"]},
  {"id": 169, "chinese": "觉得", "pinyin": "jué de", "portuguese": "sentir/achar", "categorias": ["verbo"]},
  {"id": 170, "chinese": "开始", "pinyin": "kāi shǐ", "portuguese": "começar", "categorias": ["verbo"]},
  {"id": 171, "chinese": "结束", "pinyin": "jié shù", "portuguese": "terminar", "categorias": ["verbo"]},
  {"id": 172, "chinese": "打开", "pinyin": "dǎ kāi", "portuguese": "abrir", "categorias": ["verbo"]},
  {"id": 173, "chinese": "关", "pinyin": "guān", "portuguese": "fechar", "categorias": ["verbo"]},
  {"id": 174, "chinese": "衣服", "pinyin": "yī fu", "portuguese": "roupa", "categorias": ["substantivo", "roupa"]},
  {"id": 175, "chinese": "鞋子", "pinyin": "xié zi", "portuguese": "sapato", "categorias": ["substantivo", "roupa"]},
  {"id": 176, "chinese": "帽子", "pinyin": "mào zi", "portuguese": "chapéu/boné", "categorias": ["substantivo", "roupa"]},
  {"id": 177, "chinese": "裤子", "pinyin": "kù zi", "portuguese": "calça", "categorias": ["substantivo", "roupa"]},
  {"id": 178, "chinese": "衬衫", "pinyin": "chèn shān", "portuguese": "camisa", "categorias": ["substantivo", "roupa"]},
  {"id": 179, "chinese": "裙子", "pinyin": "qún zi", "portuguese": "saia/vestido", "categorias": ["substantivo", "roupa"]},
  {"id": 180, "chinese": "钱", "pinyin": "qián", "portuguese": "dinheiro", "categorias": ["substantivo"]},
  {"id": 181, "chinese": "时间", "pinyin": "shí jiān", "portuguese": "tempo", "categorias": ["substantivo", "tempo"]},
  {"id": 182, "chinese": "人", "pinyin": "rén", "portuguese": "pessoa", "categorias": ["substantivo"]},
  {"id": 183, "chinese": "朋友", "pinyin": "péng yǒu", "portuguese": "amigo", "categorias": ["substantivo"]},
  {"id": 184, "chinese": "名字", "pinyin": "míng zi", "portuguese": "nome", "categorias": ["substantivo"]},
  {"id": 185, "chinese": "东西", "pinyin": "dōng xi", "portuguese": "coisa", "categorias": ["substantivo"]},
  {"id": 186, "chinese": "问题", "pinyin": "wèn tí", "portuguese": "problema/pergunta", "categorias": ["substantivo"]},
  {"id": 187, "chinese": "天气", "pinyin": "tiān qì", "portuguese": "clima/tempo", "categorias": ["substantivo"]},
  {"id": 188, "chinese": "身体", "pinyin": "shēn tǐ", "portuguese": "corpo", "categorias": ["substantivo"]},
  {"id": 189, "chinese": "头", "pinyin": "tóu", "portuguese": "cabeça", "categorias": ["substantivo", "corpo"]},
  {"id": 190, "chinese": "手", "pinyin": "shǒu", "portuguese": "mão", "categorias": ["substantivo", "corpo"]},
  {"id": 191, "chinese": "眼睛", "pinyin": "yǎn jīng", "portuguese": "olho", "categorias": ["substantivo", "corpo"]},
  {"id": 192, "chinese": "耳朵", "pinyin": "ěr duo", "portuguese": "orelha", "categorias": ["substantivo", "corpo"]},
  {"id": 193, "chinese": "鼻子", "pinyin": "bí zi", "portuguese": "nariz", "categorias": ["substantivo", "corpo"]},
  {"id": 194, "chinese": "嘴巴", "pinyin": "zuǐ ba", "portuguese": "boca", "categorias": ["substantivo", "corpo"]},
  {"id": 195, "chinese": "可以", "pinyin": "kě yǐ", "portuguese": "poder", "categorias": ["verbo"]},
  {"id": 196, "chinese": "需要", "pinyin": "xū yào", "portuguese": "precisar", "categorias": ["verbo"]},
  {"id": 197, "chinese": "能", "pinyin": "néng", "portuguese": "conseguir", "categorias": ["verbo"]},
  {"id": 198, "chinese": "会", "pinyin": "huì", "portuguese": "saber (fazer algo)/vai", "categorias": ["verbo"]},
  {"id": 199, "chinese": "要", "pinyin": "yào", "portuguese": "querer/precisar", "categorias": ["verbo"]},
  {"id": 200, "chinese": "有", "pinyin": "yǒu", "portuguese": "ter/existir", "categorias": ["verbo"]},
  {"id": 201, "chinese": "是", "pinyin": "shì", "portuguese": "ser/estar/sim", "categorias": ["verbo"]},
  {"id": 202, "chinese": "不", "pinyin": "bù", "portuguese": "não", "categorias": ["advérbio"]},
{"id": 203, "chinese": "很", "pinyin": "hěn", "portuguese": "muito", "categorias": ["advérbio"]},
{"id": 204, "chinese": "也", "pinyin": "yě", "portuguese": "também", "categorias": ["advérbio"]},
{"id": 205, "chinese": "都", "pinyin": "dōu", "portuguese": "todos", "categorias": ["advérbio"]},
{"id": 206, "chinese": "没", "pinyin": "méi", "portuguese": "não ter", "categorias": ["advérbio", "verbo"]},
{"id": 207, "chinese": "太", "pinyin": "tài", "portuguese": "demais/muito", "categorias": ["advérbio"]},
{"id": 208, "chinese": "最", "pinyin": "zuì", "portuguese": "o mais", "categorias": ["advérbio"]},
{"id": 209, "chinese": "真", "pinyin": "zhēn", "portuguese": "realmente/verdadeiro", "categorias": ["advérbio", "adjetivo"]},
{"id": 210, "chinese": "非常", "pinyin": "fēi cháng", "portuguese": "extremamente", "categorias": ["advérbio"]},
{"id": 211, "chinese": "经常", "pinyin": "jīng cháng", "portuguese": "frequentemente", "categorias": ["advérbio"]},
{"id": 212, "chinese": "已经", "pinyin": "yǐ jīng", "portuguese": "já", "categorias": ["advérbio"]},
{"id": 213, "chinese": "还", "pinyin": "hái", "portuguese": "ainda/também", "categorias": ["advérbio"]},
{"id": 214, "chinese": "就", "pinyin": "jiù", "portuguese": "então/logo", "categorias": ["advérbio"]},
{"id": 215, "chinese": "才", "pinyin": "cái", "portuguese": "só então/apenas", "categorias": ["advérbio"]},
{"id": 216, "chinese": "又", "pinyin": "yòu", "portuguese": "novamente", "categorias": ["advérbio"]},
{"id": 217, "chinese": "再", "pinyin": "zài", "portuguese": "de novo/mais uma vez", "categorias": ["advérbio"]},
{"id": 218, "chinese": "一起", "pinyin": "yī qǐ", "portuguese": "juntos", "categorias": ["advérbio"]},
{"id": 219, "chinese": "当然", "pinyin": "dāng rán", "portuguese": "claro/com certeza", "categorias": ["advérbio"]},
{"id": 220, "chinese": "可能", "pinyin": "kě néng", "portuguese": "talvez/possível", "categorias": ["advérbio", "verbo"]},
{"id": 221, "chinese": "但是", "pinyin": "dàn shì", "portuguese": "mas", "categorias": ["conjunção"]},
{"id": 222, "chinese": "因为", "pinyin": "yīn wèi", "portuguese": "porque", "categorias": ["conjunção"]},
{"id": 223, "chinese": "所以", "pinyin": "suǒ yǐ", "portuguese": "então/portanto", "categorias": ["conjunção"]},
{"id": 224, "chinese": "如果", "pinyin": "rú guǒ", "portuguese": "se", "categorias": ["conjunção"]},
{"id": 225, "chinese": "虽然", "pinyin": "suī rán", "portuguese": "embora", "categorias": ["conjunção"]},
{"id": 226, "chinese": "或者", "pinyin": "huò zhě", "portuguese": "ou", "categorias": ["conjunção"]},
{"id": 227, "chinese": "还是", "pinyin": "hái shì", "portuguese": "ou (em perguntas)", "categorias": ["conjunção"]},
{"id": 228, "chinese": "然后", "pinyin": "rán hòu", "portuguese": "depois/em seguida", "categorias": ["conjunção"]},
{"id": 229, "chinese": "那", "pinyin": "nà", "portuguese": "então/nesse caso", "categorias": ["conjunção"]},
{"id": 230, "chinese": "比", "pinyin": "bǐ", "portuguese": "comparado a", "categorias": ["preposição"]},
{"id": 231, "chinese": "让", "pinyin": "ràng", "portuguese": "deixar/permitir", "categorias": ["verbo"]},
{"id": 232, "chinese": "叫", "pinyin": "jiào", "portuguese": "chamar/gritar", "categorias": ["verbo"]},
{"id": 233, "chinese": "问", "pinyin": "wèn", "portuguese": "perguntar", "categorias": ["verbo"]},
{"id": 234, "chinese": "回答", "pinyin": "huí dá", "portuguese": "responder", "categorias": ["verbo"]},
{"id": 235, "chinese": "帮", "pinyin": "bāng", "portuguese": "ajudar", "categorias": ["verbo"]},
{"id": 236, "chinese": "告诉", "pinyin": "gào su", "portuguese": "contar/dizer a", "categorias": ["verbo"]},
{"id": 237, "chinese": "等", "pinyin": "děng", "portuguese": "esperar", "categorias": ["verbo"]},
{"id": 238, "chinese": "找", "pinyin": "zhǎo", "portuguese": "procurar", "categorias": ["verbo"]},
{"id": 239, "chinese": "用", "pinyin": "yòng", "portuguese": "usar", "categorias": ["verbo"]},
{"id": 240, "chinese": "做", "pinyin": "zuò", "portuguese": "fazer", "categorias": ["verbo"]},
{"id": 241, "chinese": "送", "pinyin": "sòng", "portuguese": "enviar/dar de presente", "categorias": ["verbo"]},
{"id": 242, "chinese": "带", "pinyin": "dài", "portuguese": "levar/trazer", "categorias": ["verbo"]},
{"id": 243, "chinese": "拿", "pinyin": "ná", "portuguese": "pegar/segurar", "categorias": ["verbo"]},
{"id": 244, "chinese": "放", "pinyin": "fàng", "portuguese": "colocar", "categorias": ["verbo"]},
{"id": 245, "chinese": "换", "pinyin": "huàn", "portuguese": "trocar", "categorias": ["verbo"]},
{"id": 246, "chinese": "洗", "pinyin": "xǐ", "portuguese": "lavar", "categorias": ["verbo"]},
{"id": 247, "chinese": "穿", "pinyin": "chuān", "portuguese": "vestir/usar", "categorias": ["verbo"]},
{"id": 248, "chinese": "住", "pinyin": "zhù", "portuguese": "morar/viver", "categorias": ["verbo"]},
{"id": 249, "chinese": "玩", "pinyin": "wán", "portuguese": "brincar/jogar", "categorias": ["verbo"]},
{"id": 250, "chinese": "笑", "pinyin": "xiào", "portuguese": "sorrir/rir", "categorias": ["verbo"]},
{"id": 251, "chinese": "哭", "pinyin": "kū", "portuguese": "chorar", "categorias": ["verbo"]},
{"id": 252, "chinese": "生气", "pinyin": "shēng qì", "portuguese": "ficar bravo", "categorias": ["verbo", "adjetivo"]},
{"id": 253, "chinese": "高兴", "pinyin": "gāo xìng", "portuguese": "alegre/feliz", "categorias": ["adjetivo"]},
{"id": 254, "chinese": "难过", "pinyin": "nán guò", "portuguese": "triste", "categorias": ["adjetivo"]},
{"id": 255, "chinese": "累", "pinyin": "lèi", "portuguese": "cansado", "categorias": ["adjetivo"]},
{"id": 256, "chinese": "饿", "pinyin": "è", "portuguese": "com fome", "categorias": ["adjetivo"]},
{"id": 257, "chinese": "渴", "pinyin": "kě", "portuguese": "com sede", "categorias": ["adjetivo"]},
{"id": 258, "chinese": "忙", "pinyin": "máng", "portuguese": "ocupado", "categorias": ["adjetivo"]},
{"id": 259, "chinese": "舒服", "pinyin": "shū fu", "portuguese": "confortável", "categorias": ["adjetivo"]},
{"id": 260, "chinese": "难", "pinyin": "nán", "portuguese": "difícil", "categorias": ["adjetivo"]},
{"id": 261, "chinese": "容易", "pinyin": "róng yì", "portuguese": "fácil", "categorias": ["adjetivo"]},
{"id": 262, "chinese": "对", "pinyin": "duì", "portuguese": "correto/certo", "categorias": ["adjetivo"]},
{"id": 263, "chinese": "错", "pinyin": "cuò", "portuguese": "errado", "categorias": ["adjetivo"]},
{"id": 264, "chinese": "远", "pinyin": "yuǎn", "portuguese": "longe", "categorias": ["adjetivo"]},
{"id": 265, "chinese": "近", "pinyin": "jìn", "portuguese": "perto", "categorias": ["adjetivo"]},
{"id": 266, "chinese": "便宜", "pinyin": "pián yi", "portuguese": "barato", "categorias": ["adjetivo"]},
{"id": 267, "chinese": "贵", "pinyin": "guì", "portuguese": "caro", "categorias": ["adjetivo"]},
{"id": 268, "chinese": "干", "pinyin": "gān", "portuguese": "seco", "categorias": ["adjetivo"]},
{"id": 269, "chinese": "湿", "pinyin": "shī", "portuguese": "molhado", "categorias": ["adjetivo"]},
{"id": 270, "chinese": "干净", "pinyin": "gān jìng", "portuguese": "limpo", "categorias": ["adjetivo"]},
{"id": 271, "chinese": "脏", "pinyin": "zāng", "portuguese": "sujo", "categorias": ["adjetivo"]},
{"id": 272, "chinese": "甜", "pinyin": "tián", "portuguese": "doce", "categorias": ["adjetivo"]},
{"id": 273, "chinese": "酸", "pinyin": "suān", "portuguese": "azedo", "categorias": ["adjetivo"]},
{"id": 274, "chinese": "苦", "pinyin": "kǔ", "portuguese": "amargo", "categorias": ["adjetivo"]},
{"id": 275, "chinese": "辣", "pinyin": "là", "portuguese": "picante", "categorias": ["adjetivo"]},
{"id": 276, "chinese": "咸", "pinyin": "xián", "portuguese": "salgado", "categorias": ["adjetivo"]},
{"id": 277, "chinese": "长", "pinyin": "cháng", "portuguese": "longo/comprido", "categorias": ["adjetivo"]},
{"id": 278, "chinese": "短", "pinyin": "duǎn", "portuguese": "curto", "categorias": ["adjetivo"]},
{"id": 279, "chinese": "厚", "pinyin": "hòu", "portuguese": "grosso", "categorias": ["adjetivo"]},
{"id": 280, "chinese": "薄", "pinyin": "báo", "portuguese": "fino", "categorias": ["adjetivo"]},
{"id": 281, "chinese": "重", "pinyin": "zhòng", "portuguese": "pesado", "categorias": ["adjetivo"]},
{"id": 282, "chinese": "轻", "pinyin": "qīng", "portuguese": "leve", "categorias": ["adjetivo"]},
{"id": 283, "chinese": "满", "pinyin": "mǎn", "portuguese": "cheio", "categorias": ["adjetivo"]},
{"id": 284, "chinese": "空", "pinyin": "kōng", "portuguese": "vazio", "categorias": ["adjetivo"]},
{"id": 285, "chinese": "深", "pinyin": "shēn", "portuguese": "profundo", "categorias": ["adjetivo"]},
{"id": 286, "chinese": "浅", "pinyin": "qiǎn", "portuguese": "raso", "categorias": ["adjetivo"]},
{"id": 287, "chinese": "亮", "pinyin": "liàng", "portuguese": "brilhante/claro", "categorias": ["adjetivo"]},
{"id": 288, "chinese": "暗", "pinyin": "àn", "portuguese": "escuro", "categorias": ["adjetivo"]},
{"id": 289, "chinese": "硬", "pinyin": "yìng", "portuguese": "duro", "categorias": ["adjetivo"]},
{"id": 290, "chinese": "软", "pinyin": "ruǎn", "portuguese": "macio/mole", "categorias": ["adjetivo"]},
{"id": 291, "chinese": "圆", "pinyin": "yuán", "portuguese": "redondo", "categorias": ["adjetivo"]},
{"id": 292, "chinese": "方", "pinyin": "fāng", "portuguese": "quadrado", "categorias": ["adjetivo"]},
{"id": 293, "chinese": "聪明", "pinyin": "cōng míng", "portuguese": "inteligente", "categorias": ["adjetivo"]},
{"id": 294, "chinese": "笨", "pinyin": "bèn", "portuguese": "burro/tolo", "categorias": ["adjetivo"]},
{"id": 295, "chinese": "有趣", "pinyin": "yǒu qù", "portuguese": "interessante/divertido", "categorias": ["adjetivo"]},
{"id": 296, "chinese": "无聊", "pinyin": "wú liáo", "portuguese": "chato/entediante", "categorias": ["adjetivo"]},
{"id": 297, "chinese": "安静", "pinyin": "ān jìng", "portuguese": "silencioso/calmo", "categorias": ["adjetivo"]},
{"id": 298, "chinese": "吵", "pinyin": "chǎo", "portuguese": "barulhento", "categorias": ["adjetivo"]},
{"id": 299, "chinese": "重要", "pinyin": "zhòng yào", "portuguese": "importante", "categorias": ["adjetivo"]},
{"id": 300, "chinese": "简单", "pinyin": "jiǎn dān", "portuguese": "simples", "categorias": ["adjetivo"]},
{"id": 301, "chinese": "复杂", "pinyin": "fù zá", "portuguese": "complexo", "categorias": ["adjetivo"]},
{"id": 302, "chinese": "安全", "pinyin": "ān quán", "portuguese": "seguro", "categorias": ["adjetivo"]},
{"id": 303, "chinese": "危险", "pinyin": "wēi xiǎn", "portuguese": "perigoso", "categorias": ["adjetivo"]},
{"id": 304, "chinese": "健康", "pinyin": "jiàn kāng", "portuguese": "saudável", "categorias": ["adjetivo"]},
{"id": 305, "chinese": "生病", "pinyin": "shēng bìng", "portuguese": "doente", "categorias": ["adjetivo", "verbo"]},
{"id": 306, "chinese": "疼", "pinyin": "téng", "portuguese": "doer/dolorido", "categorias": ["adjetivo", "verbo"]},
{"id": 307, "chinese": "累", "pinyin": "lèi", "portuguese": "cansado", "categorias": ["adjetivo"]},
{"id": 308, "chinese": "困", "pinyin": "kùn", "portuguese": "com sono", "categorias": ["adjetivo"]},
{"id": 309, "chinese": "动物", "pinyin": "dòng wù", "portuguese": "animal", "categorias": ["substantivo", "animal"]},
{"id": 310, "chinese": "熊猫", "pinyin": "xióng māo", "portuguese": "panda", "categorias": ["animal"]},
{"id": 311, "chinese": "大象", "pinyin": "dà xiàng", "portuguese": "elefante", "categorias": ["animal"]},
{"id": 312, "chinese": "猴子", "pinyin": "hóu zi", "portuguese": "macaco", "categorias": ["animal"]},
{"id": 313, "chinese": "狮子", "pinyin": "shī zi", "portuguese": "leão", "categorias": ["animal"]},
{"id": 314, "chinese": "蛇", "pinyin": "shé", "portuguese": "cobra/serpente", "categorias": ["animal"]},
{"id": 315, "chinese": "老鼠", "pinyin": "lǎo shǔ", "portuguese": "rato", "categorias": ["animal"]},
{"id": 316, "chinese": "鸭子", "pinyin": "yā zi", "portuguese": "pato", "categorias": ["animal"]},
{"id": 317, "chinese": "鹅", "pinyin": "é", "portuguese": "ganso", "categorias": ["animal"]},
{"id": 318, "chinese": "熊猫", "pinyin": "xióng māo", "portuguese": "panda", "categorias": ["animal"]},
{"id": 319, "chinese": "虫子", "pinyin": "chóng zi", "portuguese": "inseto/verme", "categorias": ["animal"]},
{"id": 320, "chinese": "乌龟", "pinyin": "wū guī", "portuguese": "tartaruga", "categorias": ["animal"]},
{"id": 321, "chinese": "青蛙", "pinyin": "qīng wā", "portuguese": "sapo/rã", "categorias": ["animal"]},
{"id": 322, "chinese": "蝴蝶", "pinyin": "hú dié", "portuguese": "borboleta", "categorias": ["animal"]},
{"id": 323, "chinese": "蜜蜂", "pinyin": "mì fēng", "portuguese": "abelha", "categorias": ["animal"]},
{"id": 324, "chinese": "蚂蚁", "pinyin": "mǎ yǐ", "portuguese": "formiga", "categorias": ["animal"]},
{"id": 325, "chinese": "花", "pinyin": "huā", "portuguese": "flor", "categorias": ["substantivo", "natureza"]},
{"id": 326, "chinese": "树", "pinyin": "shù", "portuguese": "árvore", "categorias": ["substantivo", "natureza"]},
{"id": 327, "chinese": "草", "pinyin": "cǎo", "portuguese": "grama", "categorias": ["substantivo", "natureza"]},
{"id": 328, "chinese": "叶子", "pinyin": "yè zi", "portuguese": "folha", "categorias": ["substantivo", "natureza"]},
{"id": 329, "chinese": "太阳", "pinyin": "tài yáng", "portuguese": "sol", "categorias": ["substantivo", "natureza"]},
{"id": 330, "chinese": "月亮", "pinyin": "yuè liang", "portuguese": "lua", "categorias": ["substantivo", "natureza"]},
{"id": 331, "chinese": "星星", "pinyin": "xīng xīng", "portuguese": "estrela", "categorias": ["substantivo", "natureza"]},
{"id": 332, "chinese": "天空", "pinyin": "tiān kōng", "portuguese": "céu", "categorias": ["substantivo", "natureza"]},
{"id": 333, "chinese": "云", "pinyin": "yún", "portuguese": "nuvem", "categorias": ["substantivo", "natureza"]},
{"id": 334, "chinese": "雨", "pinyin": "yǔ", "portuguese": "chuva", "categorias": ["substantivo", "natureza"]},
{"id": 335, "chinese": "雪", "pinyin": "xuě", "portuguese": "neve", "categorias": ["substantivo", "natureza"]},
{"id": 336, "chinese": "风", "pinyin": "fēng", "portuguese": "vento", "categorias": ["substantivo", "natureza"]},
{"id": 337, "chinese": "山", "pinyin": "shān", "portuguese": "montanha", "categorias": ["substantivo", "natureza"]},
{"id": 338, "chinese": "海", "pinyin": "hǎi", "portuguese": "mar", "categorias": ["substantivo", "natureza"]},
{"id": 339, "chinese": "河", "pinyin": "hé", "portuguese": "rio", "categorias": ["substantivo", "natureza"]},
{"id": 340, "chinese": "湖", "pinyin": "hú", "portuguese": "lago", "categorias": ["substantivo", "natureza"]},
{"id": 341, "chinese": "石头", "pinyin": "shí tou", "portuguese": "pedra", "categorias": ["substantivo", "natureza"]},
{"id": 342, "chinese": "火", "pinyin": "huǒ", "portuguese": "fogo", "categorias": ["substantivo", "natureza"]},
{"id": 343, "chinese": "空气", "pinyin": "kōng qì", "portuguese": "ar", "categorias": ["substantivo", "natureza"]},
{"id": 344, "chinese": "地图", "pinyin": "dì tú", "portuguese": "mapa", "categorias": ["substantivo", "objeto"]},
{"id": 345, "chinese": "照片", "pinyin": "zhào piàn", "portuguese": "foto", "categorias": ["substantivo", "objeto"]},
{"id": 346, "chinese": "报纸", "pinyin": "bào zhǐ", "portuguese": "jornal", "categorias": ["substantivo", "objeto"]},
{"id": 347, "chinese": "杂志", "pinyin": "zá zhì", "portuguese": "revista", "categorias": ["substantivo", "objeto"]},
{"id": 348, "chinese": "笔", "pinyin": "bǐ", "portuguese": "caneta", "categorias": ["substantivo", "objeto"]},
{"id": 349, "chinese": "纸", "pinyin": "zhǐ", "portuguese": "papel", "categorias": ["substantivo", "objeto"]},
{"id": 350, "chinese": "橡皮", "pinyin": "xiàng pí", "portuguese": "borracha", "categorias": ["substantivo", "objeto"]},
{"id": 351, "chinese": "尺子", "pinyin": "chǐ zi", "portuguese": "régua", "categorias": ["substantivo", "objeto"]},
{"id": 352, "chinese": "书包", "pinyin": "shū bāo", "portuguese": "mochila escolar", "categorias": ["substantivo", "objeto"]},
{"id": 353, "chinese": "雨伞", "pinyin": "yǔ sǎn", "portuguese": "guarda-chuva", "categorias": ["substantivo", "objeto"]},
{"id": 354, "chinese": "钥匙", "pinyin": "yào shi", "portuguese": "chave", "categorias": ["substantivo", "objeto"]},
{"id": 355, "chinese": "杯子", "pinyin": "bēi zi", "portuguese": "copo/xícara", "categorias": ["substantivo", "objeto"]},
{"id": 356, "chinese": "盘子", "pinyin": "pán zi", "portuguese": "prato", "categorias": ["substantivo", "objeto"]},
{"id": 357, "chinese": "碗", "pinyin": "wǎn", "portuguese": "tigela", "categorias": ["substantivo", "objeto"]},
{"id": 358, "chinese": "筷子", "pinyin": "kuài zi", "portuguese": "hashi/pauzinhos", "categorias": ["substantivo", "objeto"]},
{"id": 359, "chinese": "勺子", "pinyin": "sháo zi", "portuguese": "colher", "categorias": ["substantivo", "objeto"]},
{"id": 360, "chinese": "刀", "pinyin": "dāo", "portuguese": "faca", "categorias": ["substantivo", "objeto"]},
{"id": 361, "chinese": "叉子", "pinyin": "chā zi", "portuguese": "garfo", "categorias": ["substantivo", "objeto"]},
{"id": 362, "chinese": "瓶子", "pinyin": "píng zi", "portuguese": "garrafa", "categorias": ["substantivo", "objeto"]},
{"id": 363, "chinese": "盒子", "pinyin": "hé zi", "portuguese": "caixa", "categorias": ["substantivo", "objeto"]},
{"id": 364, "chinese": "袋子", "pinyin": "dài zi", "portuguese": "sacola/bolsa", "categorias": ["substantivo", "objeto"]},
{"id": 365, "chinese": "包", "pinyin": "bāo", "portuguese": "bolsa/mochila", "categorias": ["substantivo", "objeto"]},
{"id": 366, "chinese": "手表", "pinyin": "shǒu biǎo", "portuguese": "relógio de pulso", "categorias": ["substantivo", "objeto"]},
{"id": 367, "chinese": "镜子", "pinyin": "jìng zi", "portuguese": "espelho", "categorias": ["substantivo", "objeto"]},
{"id": 368, "chinese": "眼镜", "pinyin": "yǎn jìng", "portuguese": "óculos", "categorias": ["substantivo", "objeto"]},
{"id": 369, "chinese": "礼物", "pinyin": "lǐ wù", "portuguese": "presente", "categorias": ["substantivo"]},
{"id": 370, "chinese": "信", "pinyin": "xìn", "portuguese": "carta", "categorias": ["substantivo"]},
{"id": 371, "chinese": "票", "pinyin": "piào", "portuguese": "bilhete/ingresso", "categorias": ["substantivo"]},
{"id": 372, "chinese": "药", "pinyin": "yào", "portuguese": "remédio", "categorias": ["substantivo"]},
{"id": 373, "chinese": "糖", "pinyin": "táng", "portuguese": "açúcar/doce", "categorias": ["substantivo", "comida"]},
{"id": 374, "chinese": "盐", "pinyin": "yán", "portuguese": "sal", "categorias": ["substantivo", "comida"]},
{"id": 375, "chinese": "油", "pinyin": "yóu", "portuguese": "óleo/gordura", "categorias": ["substantivo", "comida"]},
{"id": 376, "chinese": "酱油", "pinyin": "jiàng yóu", "portuguese": "molho de soja", "categorias": ["comida"]},
{"id": 377, "chinese": "醋", "pinyin": "cù", "portuguese": "vinagre", "categorias": ["comida"]},
{"id": 378, "chinese": "辣椒", "pinyin": "là jiāo", "portuguese": "pimenta", "categorias": ["comida"]},
{"id": 379, "chinese": "大蒜", "pinyin": "dà suàn", "portuguese": "alho", "categorias": ["comida"]},
{"id": 380, "chinese": "姜", "pinyin": "jiāng", "portuguese": "gengibre", "categorias": ["comida"]},
{"id": 381, "chinese": "洋葱", "pinyin": "yáng cōng", "portuguese": "cebola", "categorias": ["comida"]},
{"id": 382, "chinese": "土豆", "pinyin": "tǔ dòu", "portuguese": "batata", "categorias": ["comida"]},
{"id": 383, "chinese": "西红柿", "pinyin": "xī hóng shì", "portuguese": "tomate", "categorias": ["comida"]},
{"id": 384, "chinese": "黄瓜", "pinyin": "huáng guā", "portuguese": "pepino", "categorias": ["comida"]},
{"id": 385, "chinese": "胡萝卜", "pinyin": "hú luó bo", "portuguese": "cenoura", "categorias": ["comida"]},
{"id": 386, "chinese": "白菜", "pinyin": "bái cài", "portuguese": "acelga/repolho chinês", "categorias": ["comida"]},
{"id": 387, "chinese": "蘑菇", "pinyin": "mó gu", "portuguese": "cogumelo", "categorias": ["comida"]},
{"id": 388, "chinese": "肉", "pinyin": "ròu", "portuguese": "carne", "categorias": ["comida"]},
{"id": 389, "chinese": "牛肉", "pinyin": "niú ròu", "portuguese": "carne de vaca", "categorias": ["comida"]},
{"id": 390, "chinese": "猪肉", "pinyin": "zhū ròu", "portuguese": "carne de porco", "categorias": ["comida"]},
{"id": 391, "chinese": "鸡肉", "pinyin": "jī ròu", "portuguese": "frango", "categorias": ["comida"]},
{"id": 392, "chinese": "羊肉", "pinyin": "yáng ròu", "portuguese": "carne de cordeiro", "categorias": ["comida"]},
{"id": 393, "chinese": "鱼", "pinyin": "yú", "portuguese": "peixe", "categorias": ["comida"]},
{"id": 394, "chinese": "虾", "pinyin": "xiā", "portuguese": "camarão", "categorias": ["comida"]},
{"id": 395, "chinese": "螃蟹", "pinyin": "páng xiè", "portuguese": "caranguejo", "categorias": ["comida"]},
{"id": 396, "chinese": "蛋糕", "pinyin": "dàn gāo", "portuguese": "bolo", "categorias": ["comida"]},
{"id": 397, "chinese": "饼干", "pinyin": "bǐng gān", "portuguese": "biscoito/bolacha", "categorias": ["comida"]},
{"id": 398, "chinese": "巧克力", "pinyin": "qiǎo kè lì", "portuguese": "chocolate", "categorias": ["comida"]},
{"id": 399, "chinese": "冰淇淋", "pinyin": "bīng qí lín", "portuguese": "sorvete", "categorias": ["comida"]},
{"id": 400, "chinese": "汤", "pinyin": "tāng", "portuguese": "sopa", "categorias": ["comida"]},
{"id": 401, "chinese": "炒饭", "pinyin": "chǎo fàn", "portuguese": "arroz frito", "categorias": ["comida"]},
{"id": 402, "chinese": "炒面", "pinyin": "chǎo miàn", "portuguese": "macarrão frito", "categorias": ["comida"]},
{"id": 403, "chinese": "春卷", "pinyin": "chūn juǎn", "portuguese": "rolinho primavera", "categorias": ["comida"]},
{"id": 404, "chinese": "粥", "pinyin": "zhōu", "portuguese": "mingau de arroz", "categorias": ["comida"]},
{"id": 405, "chinese": "早餐", "pinyin": "zǎo cān", "portuguese": "café da manhã", "categorias": ["comida", "tempo"]},
{"id": 406, "chinese": "午餐", "pinyin": "wǔ cān", "portuguese": "almoço", "categorias": ["comida", "tempo"]},
{"id": 407, "chinese": "晚餐", "pinyin": "wǎn cān", "portuguese": "jantar", "categorias": ["comida", "tempo"]},
{"id": 408, "chinese": "蔬菜", "pinyin": "shū cài", "portuguese": "verduras/legumes", "categorias": ["comida"]},
{"id": 409, "chinese": "饮料", "pinyin": "yǐn liào", "portuguese": "bebida", "categorias": ["bebida"]},
{"id": 410, "chinese": "红酒", "pinyin": "hóng jiǔ", "portuguese": "vinho tinto", "categorias": ["bebida"]},
{"id": 411, "chinese": "白酒", "pinyin": "bái jiǔ", "portuguese": "aguardente chinês", "categorias": ["bebida"]},
{"id": 412, "chinese": "矿泉水", "pinyin": "kuàng quán shuǐ", "portuguese": "água mineral", "categorias": ["bebida"]},
{"id": 413, "chinese": "橙汁", "pinyin": "chéng zhī", "portuguese": "suco de laranja", "categorias": ["bebida"]},
{"id": 414, "chinese": "葡萄汁", "pinyin": "pú tao zhī", "portuguese": "suco de uva", "categorias": ["bebida"]},
{"id": 415, "chinese": "苹果汁", "pinyin": "píng guǒ zhī", "portuguese": "suco de maçã", "categorias": ["bebida"]},
{"id": 416, "chinese": "豆浆", "pinyin": "dòu jiāng", "portuguese": "leite de soja", "categorias": ["bebida"]},
{"id": 417, "chinese": "酸奶", "pinyin": "suān nǎi", "portuguese": "iogurte", "categorias": ["bebida", "comida"]},
{"id": 418, "chinese": "冰水", "pinyin": "bīng shuǐ", "portuguese": "água gelada", "categorias": ["bebida"]},
{"id": 419, "chinese": "热水", "pinyin": "rè shuǐ", "portuguese": "água quente", "categorias": ["bebida"]},
{"id": 420, "chinese": "绿茶", "pinyin": "lǜ chá", "portuguese": "chá verde", "categorias": ["bebida"]},
{"id": 421, "chinese": "红茶", "pinyin": "hóng chá", "portuguese": "chá preto", "categorias": ["bebida"]},
{"id": 422, "chinese": "花茶", "pinyin": "huā chá", "portuguese": "chá de flores", "categorias": ["bebida"]},
{"id": 423, "chinese": "教室", "pinyin": "jiào shì", "portuguese": "sala de aula", "categorias": ["lugar"]},
{"id": 424, "chinese": "办公室", "pinyin": "bàn gōng shì", "portuguese": "escritório", "categorias": ["lugar"]},
{"id": 425, "chinese": "图书馆", "pinyin": "tú shū guǎn", "portuguese": "biblioteca", "categorias": ["lugar"]},
{"id": 426, "chinese": "厕所", "pinyin": "cè suǒ", "portuguese": "banheiro", "categorias": ["lugar"]},
{"id": 427, "chinese": "厨房", "pinyin": "chú fáng", "portuguese": "cozinha", "categorias": ["lugar"]},
{"id": 428, "chinese": "卧室", "pinyin": "wò shì", "portuguese": "quarto", "categorias": ["lugar"]},
{"id": 429, "chinese": "客厅", "pinyin": "kè tīng", "portuguese": "sala de estar", "categorias": ["lugar"]},
{"id": 430, "chinese": "花园", "pinyin": "huā yuán", "portuguese": "jardim", "categorias": ["lugar"]},
{"id": 431, "chinese": "游泳池", "pinyin": "yóu yǒng chí", "portuguese": "piscina", "categorias": ["lugar"]},
{"id": 432, "chinese": "健身房", "pinyin": "jiàn shēn fáng", "portuguese": "academia", "categorias": ["lugar"]},
{"id": 433, "chinese": "电影院", "pinyin": "diàn yǐng yuàn", "portuguese": "cinema", "categorias": ["lugar"]},
{"id": 434, "chinese": "博物馆", "pinyin": "bó wù guǎn", "portuguese": "museu", "categorias": ["lugar"]},
{"id": 435, "chinese": "教堂", "pinyin": "jiào táng", "portuguese": "igreja", "categorias": ["lugar"]},
{"id": 436, "chinese": "寺庙", "pinyin": "sì miào", "portuguese": "templo", "categorias": ["lugar"]},
{"id": 437, "chinese": "邮局", "pinyin": "yóu jú", "portuguese": "correio", "categorias": ["lugar"]},
{"id": 438, "chinese": "警察局", "pinyin": "jǐng chá jú", "portuguese": "delegacia", "categorias": ["lugar"]},
{"id": 439, "chinese": "市政府", "pinyin": "shì zhèng fǔ", "portuguese": "prefeitura", "categorias": ["lugar"]},
{"id": 440, "chinese": "广场", "pinyin": "guǎng chǎng", "portuguese": "praça", "categorias": ["lugar"]},
{"id": 441, "chinese": "桥", "pinyin": "qiáo", "portuguese": "ponte", "categorias": ["lugar"]},
{"id": 442, "chinese": "路", "pinyin": "lù", "portuguese": "rua/estrada", "categorias": ["lugar"]},
{"id": 443, "chinese": "街", "pinyin": "jiē", "portuguese": "rua", "categorias": ["lugar"]},
{"id": 444, "chinese": "城市", "pinyin": "chéng shì", "portuguese": "cidade", "categorias": ["lugar"]},
{"id": 445, "chinese": "农村", "pinyin": "nóng cūn", "portuguese": "campo/zona rural", "categorias": ["lugar"]},
{"id": 446, "chinese": "国家", "pinyin": "guó jiā", "portuguese": "país", "categorias": ["lugar"]},
{"id": 447, "chinese": "中国", "pinyin": "zhōng guó", "portuguese": "China", "categorias": ["lugar"]},
{"id": 448, "chinese": "巴西", "pinyin": "bā xī", "portuguese": "Brasil", "categorias": ["lugar"]},
{"id": 449, "chinese": "美国", "pinyin": "měi guó", "portuguese": "Estados Unidos", "categorias": ["lugar"]},
{"id": 450, "chinese": "日本", "pinyin": "rì běn", "portuguese": "Japão", "categorias": ["lugar"]},
{"id": 451, "chinese": "英国", "pinyin": "yīng guó", "portuguese": "Inglaterra", "categorias": ["lugar"]},
{"id": 452, "chinese": "法国", "pinyin": "fǎ guó", "portuguese": "França", "categorias": ["lugar"]},
{"id": 453, "chinese": "德国", "pinyin": "dé guó", "portuguese": "Alemanha", "categorias": ["lugar"]},
{"id": 454, "chinese": "北京", "pinyin": "běi jīng", "portuguese": "Pequim", "categorias": ["lugar"]},
{"id": 455, "chinese": "上海", "pinyin": "shàng hǎi", "portuguese": "Xangai", "categorias": ["lugar"]},
{"id": 456, "chinese": "香港", "pinyin": "xiāng gǎng", "portuguese": "Hong Kong", "categorias": ["lugar"]},
{"id": 457, "chinese": "台湾", "pinyin": "tái wān", "portuguese": "Taiwan", "categorias": ["lugar"]},
{"id": 458, "chinese": "中文", "pinyin": "zhōng wén", "portuguese": "língua chinesa", "categorias": ["substantivo"]},
{"id": 459, "chinese": "英文", "pinyin": "yīng wén", "portuguese": "inglês", "categorias": ["substantivo"]},
{"id": 460, "chinese": "葡萄牙语", "pinyin": "pú táo yá yǔ", "portuguese": "português", "categorias": ["substantivo"]},
{"id": 461, "chinese": "汉字", "pinyin": "hàn zì", "portuguese": "caractere chinês", "categorias": ["substantivo"]},
{"id": 462, "chinese": "拼音", "pinyin": "pīn yīn", "portuguese": "pinyin", "categorias": ["substantivo"]},
{"id": 463, "chinese": "意思", "pinyin": "yì si", "portuguese": "significado", "categorias": ["substantivo"]},
{"id": 464, "chinese": "句子", "pinyin": "jù zi", "portuguese": "frase", "categorias": ["substantivo"]},
{"id": 465, "chinese": "单词", "pinyin": "dān cí", "portuguese": "palavra", "categorias": ["substantivo"]},
{"id": 466, "chinese": "故事", "pinyin": "gù shì", "portuguese": "história/conto", "categorias": ["substantivo"]},
{"id": 467, "chinese": "音乐", "pinyin": "yīn yuè", "portuguese": "música", "categorias": ["substantivo"]},
{"id": 468, "chinese": "歌", "pinyin": "gē", "portuguese": "canção", "categorias": ["substantivo"]},
{"id": 469, "chinese": "电影", "pinyin": "diàn yǐng", "portuguese": "filme", "categorias": ["substantivo"]},
{"id": 470, "chinese": "游戏", "pinyin": "yóu xì", "portuguese": "jogo", "categorias": ["substantivo"]},
{"id": 471, "chinese": "运动", "pinyin": "yùn dòng", "portuguese": "esporte/exercício", "categorias": ["substantivo"]},
{"id": 472, "chinese": "足球", "pinyin": "zú qiú", "portuguese": "futebol", "categorias": ["substantivo"]},
{"id": 473, "chinese": "篮球", "pinyin": "lán qiú", "portuguese": "basquete", "categorias": ["substantivo"]},
{"id": 474, "chinese": "排球", "pinyin": "pái qiú", "portuguese": "vôlei", "categorias": ["substantivo"]},
{"id": 475, "chinese": "网球", "pinyin": "wǎng qiú", "portuguese": "tênis", "categorias": ["substantivo"]},
{"id": 476, "chinese": "游泳", "pinyin": "yóu yǒng", "portuguese": "natação/nadar", "categorias": ["verbo", "substantivo"]},
{"id": 477, "chinese": "跑步", "pinyin": "pǎo bù", "portuguese": "corrida/correr", "categorias": ["verbo", "substantivo"]},
{"id": 478, "chinese": "跳舞", "pinyin": "tiào wǔ", "portuguese": "dançar/dança", "categorias": ["verbo", "substantivo"]},
{"id": 479, "chinese": "唱歌", "pinyin": "chàng gē", "portuguese": "cantar", "categorias": ["verbo"]},
{"id": 480, "chinese": "画画", "pinyin": "huà huà", "portuguese": "desenhar/pintar", "categorias": ["verbo"]},
{"id": 481, "chinese": "拍照", "pinyin": "pāi zhào", "portuguese": "tirar foto", "categorias": ["verbo"]},
{"id": 482, "chinese": "旅游", "pinyin": "lǚ yóu", "portuguese": "viajar/turismo", "categorias": ["verbo", "substantivo"]},
{"id": 483, "chinese": "开车", "pinyin": "kāi chē", "portuguese": "dirigir", "categorias": ["verbo"]},
{"id": 484, "chinese": "坐飞机", "pinyin": "zuò fēi jī", "portuguese": "andar de avião", "categorias": ["verbo"]},
{"id": 485, "chinese": "坐火车", "pinyin": "zuò huǒ chē", "portuguese": "andar de trem", "categorias": ["verbo"]},
{"id": 486, "chinese": "骑自行车", "pinyin": "qí zì xíng chē", "portuguese": "andar de bicicleta", "categorias": ["verbo"]},
{"id": 487, "chinese": "公共汽车", "pinyin": "gōng gòng qì chē", "portuguese": "ônibus", "categorias": ["substantivo"]},
{"id": 488, "chinese": "地铁", "pinyin": "dì tiě", "portuguese": "metrô", "categorias": ["substantivo"]},
{"id": 489, "chinese": "出租车", "pinyin": "chū zū chē", "portuguese": "táxi", "categorias": ["substantivo"]},
{"id": 490, "chinese": "飞机", "pinyin": "fēi jī", "portuguese": "avião", "categorias": ["substantivo"]},
{"id": 491, "chinese": "火车", "pinyin": "huǒ chē", "portuguese": "trem", "categorias": ["substantivo"]},
{"id": 492, "chinese": "船", "pinyin": "chuán", "portuguese": "barco/navio", "categorias": ["substantivo"]},
{"id": 493, "chinese": "自行车", "pinyin": "zì xíng chē", "portuguese": "bicicleta", "categorias": ["substantivo"]},
{"id": 494, "chinese": "摩托车", "pinyin": "mó tuō chē", "portuguese": "moto", "categorias": ["substantivo"]},
{"id": 495, "chinese": "车", "pinyin": "chē", "portuguese": "carro/veículo", "categorias": ["substantivo"]},
{"id": 496, "chinese": "衬衫", "pinyin": "chèn shān", "portuguese": "camisa", "categorias": ["roupa"]},
{"id": 497, "chinese": "T恤", "pinyin": "T xù", "portuguese": "camiseta", "categorias": ["roupa"]},
{"id": 498, "chinese": "外套", "pinyin": "wài tào", "portuguese": "casaco/jaqueta", "categorias": ["roupa"]},
{"id": 499, "chinese": "毛衣", "pinyin": "máo yī", "portuguese": "suéter", "categorias": ["roupa"]},
{"id": 500, "chinese": "围巾", "pinyin": "wéi jīn", "portuguese": "cachecol", "categorias": ["roupa"]},
{"id": 501, "chinese": "手套", "pinyin": "shǒu tào", "portuguese": "luvas", "categorias": ["roupa"]},
{"id": 502, "chinese": "袜子", "pinyin": "wà zi", "portuguese": "meias", "categorias": ["roupa"]},
{"id": 503, "chinese": "内衣", "pinyin": "nèi yī", "portuguese": "roupa íntima", "categorias": ["roupa"]},
{"id": 504, "chinese": "睡衣", "pinyin": "shuì yī", "portuguese": "pijama", "categorias": ["roupa"]},
{"id": 505, "chinese": "游泳衣", "pinyin": "yóu yǒng yī", "portuguese": "roupa de banho", "categorias": ["roupa"]},
{"id": 506, "chinese": "短裤", "pinyin": "duǎn kù", "portuguese": "shorts/bermuda", "categorias": ["roupa"]},
{"id": 507, "chinese": "领带", "pinyin": "lǐng dài", "portuguese": "gravata", "categorias": ["roupa"]},
{"id": 508, "chinese": "口袋", "pinyin": "kǒu dài", "portuguese": "bolso", "categorias": ["roupa"]},
{"id": 509, "chinese": "拉链", "pinyin": "lā liàn", "portuguese": "zíper", "categorias": ["roupa"]},
{"id": 510, "chinese": "纽扣", "pinyin": "niǔ kòu", "portuguese": "botão", "categorias": ["roupa"]},
{"id": 511, "chinese": "腿", "pinyin": "tuǐ", "portuguese": "perna", "categorias": ["substantivo", "corpo"]},
{"id": 512, "chinese": "脚", "pinyin": "jiǎo", "portuguese": "pé", "categorias": ["substantivo", "corpo"]},
{"id": 513, "chinese": "胳膊", "pinyin": "gē bo", "portuguese": "braço", "categorias": ["substantivo", "corpo"]},
{"id": 514, "chinese": "手指", "pinyin": "shǒu zhǐ", "portuguese": "dedo da mão", "categorias": ["substantivo", "corpo"]},
{"id": 515, "chinese": "脚趾", "pinyin": "jiǎo zhǐ", "portuguese": "dedo do pé", "categorias": ["substantivo", "corpo"]},
{"id": 516, "chinese": "肩膀", "pinyin": "jiān bǎng", "portuguese": "ombro", "categorias": ["substantivo", "corpo"]},
{"id": 517, "chinese": "膝盖", "pinyin": "xī gài", "portuguese": "joelho", "categorias": ["substantivo", "corpo"]},
{"id": 518, "chinese": "脖子", "pinyin": "bó zi", "portuguese": "pescoço", "categorias": ["substantivo", "corpo"]},
{"id": 519, "chinese": "背", "pinyin": "bèi", "portuguese": "costas", "categorias": ["substantivo", "corpo"]},
{"id": 520, "chinese": "肚子", "pinyin": "dù zi", "portuguese": "barriga", "categorias": ["substantivo", "corpo"]},
{"id": 521, "chinese": "牙齿", "pinyin": "yá chǐ", "portuguese": "dente", "categorias": ["substantivo", "corpo"]},
{"id": 522, "chinese": "舌头", "pinyin": "shé tou", "portuguese": "língua", "categorias": ["substantivo", "corpo"]},
{"id": 523, "chinese": "头发", "pinyin": "tóu fa", "portuguese": "cabelo", "categorias": ["substantivo", "corpo"]},
{"id": 524, "chinese": "脸", "pinyin": "liǎn", "portuguese": "rosto", "categorias": ["substantivo", "corpo"]},
{"id": 525, "chinese": "皮肤", "pinyin": "pí fū", "portuguese": "pele", "categorias": ["substantivo", "corpo"]},
{"id": 526, "chinese": "骨头", "pinyin": "gǔ tou", "portuguese": "osso", "categorias": ["substantivo", "corpo"]},
{"id": 527, "chinese": "血", "pinyin": "xuè", "portuguese": "sangue", "categorias": ["substantivo", "corpo"]},
{"id": 528, "chinese": "心", "pinyin": "xīn", "portuguese": "coração", "categorias": ["substantivo", "corpo"]},
{"id": 529, "chinese": "声音", "pinyin": "shēng yīn", "portuguese": "voz/som", "categorias": ["substantivo"]},
{"id": 530, "chinese": "力气", "pinyin": "lì qi", "portuguese": "força", "categorias": ["substantivo"]},
{"id": 531, "chinese": "梦", "pinyin": "mèng", "portuguese": "sonho", "categorias": ["substantivo"]},
{"id": 532, "chinese": "主意", "pinyin": "zhǔ yi", "portuguese": "ideia/opinião", "categorias": ["substantivo"]},
{"id": 533, "chinese": "办法", "pinyin": "bàn fǎ", "portuguese": "método/solução", "categorias": ["substantivo"]},
{"id": 534, "chinese": "机会", "pinyin": "jī huì", "portuguese": "oportunidade", "categorias": ["substantivo"]},
{"id": 535, "chinese": "关系", "pinyin": "guān xi", "portuguese": "relação/conexão", "categorias": ["substantivo"]},
{"id": 536, "chinese": "原因", "pinyin": "yuán yīn", "portuguese": "razão/motivo", "categorias": ["substantivo"]},
{"id": 537, "chinese": "结果", "pinyin": "jié guǒ", "portuguese": "resultado", "categorias": ["substantivo"]},
{"id": 538, "chinese": "样子", "pinyin": "yàng zi", "portuguese": "aparência/jeito", "categorias": ["substantivo"]},
{"id": 539, "chinese": "方面", "pinyin": "fāng miàn", "portuguese": "aspecto/lado", "categorias": ["substantivo"]},
{"id": 540, "chinese": "情况", "pinyin": "qíng kuàng", "portuguese": "situação", "categorias": ["substantivo"]},
{"id": 541, "chinese": "习惯", "pinyin": "xí guàn", "portuguese": "hábito/costume", "categorias": ["substantivo"]},
{"id": 542, "chinese": "文化", "pinyin": "wén huà", "portuguese": "cultura", "categorias": ["substantivo"]},
{"id": 543, "chinese": "历史", "pinyin": "lì shǐ", "portuguese": "história", "categorias": ["substantivo"]},
{"id": 544, "chinese": "科学", "pinyin": "kē xué", "portuguese": "ciência", "categorias": ["substantivo"]},
{"id": 545, "chinese": "数学", "pinyin": "shù xué", "portuguese": "matemática", "categorias": ["substantivo"]},
{"id": 546, "chinese": "艺术", "pinyin": "yì shù", "portuguese": "arte", "categorias": ["substantivo"]},
{"id": 547, "chinese": "体育", "pinyin": "tǐ yù", "portuguese": "educação física", "categorias": ["substantivo"]},
{"id": 548, "chinese": "教育", "pinyin": "jiào yù", "portuguese": "educação", "categorias": ["substantivo"]},
{"id": 549, "chinese": "经济", "pinyin": "jīng jì", "portuguese": "economia", "categorias": ["substantivo"]},
{"id": 550, "chinese": "政治", "pinyin": "zhèng zhì", "portuguese": "política", "categorias": ["substantivo"]},
{"id": 551, "chinese": "法律", "pinyin": "fǎ lǜ", "portuguese": "lei/direito", "categorias": ["substantivo"]},
{"id": 552, "chinese": "社会", "pinyin": "shè huì", "portuguese": "sociedade", "categorias": ["substantivo"]},
{"id": 553, "chinese": "环境", "pinyin": "huán jìng", "portuguese": "meio ambiente", "categorias": ["substantivo"]},
{"id": 554, "chinese": "世界", "pinyin": "shì jiè", "portuguese": "mundo", "categorias": ["substantivo"]},
{"id": 555, "chinese": "生活", "pinyin": "shēng huó", "portuguese": "vida/viver", "categorias": ["substantivo", "verbo"]},
{"id": 556, "chinese": "幸福", "pinyin": "xìng fú", "portuguese": "felicidade/feliz", "categorias": ["substantivo", "adjetivo"]},
{"id": 557, "chinese": "希望", "pinyin": "xī wàng", "portuguese": "esperança/esperar", "categorias": ["substantivo", "verbo"]},
{"id": 558, "chinese": "成功", "pinyin": "chéng gōng", "portuguese": "sucesso/ter sucesso", "categorias": ["substantivo", "verbo"]},
{"id": 559, "chinese": "失败", "pinyin": "shī bài", "portuguese": "fracasso/fracassar", "categorias": ["substantivo", "verbo"]},
{"id": 560, "chinese": "经验", "pinyin": "jīng yàn", "portuguese": "experiência", "categorias": ["substantivo"]},
{"id": 561, "chinese": "水平", "pinyin": "shuǐ píng", "portuguese": "nível", "categorias": ["substantivo"]},
{"id": 562, "chinese": "提高", "pinyin": "tí gāo", "portuguese": "melhorar/aumentar", "categorias": ["verbo"]},
{"id": 563, "chinese": "改变", "pinyin": "gǎi biàn", "portuguese": "mudar/transformar", "categorias": ["verbo"]},
{"id": 564, "chinese": "发展", "pinyin": "fā zhǎn", "portuguese": "desenvolver", "categorias": ["verbo"]},
{"id": 565, "chinese": "参加", "pinyin": "cān jiā", "portuguese": "participar", "categorias": ["verbo"]},
{"id": 566, "chinese": "准备", "pinyin": "zhǔn bèi", "portuguese": "preparar", "categorias": ["verbo"]},
{"id": 567, "chinese": "决定", "pinyin": "jué dìng", "portuguese": "decidir", "categorias": ["verbo"]},
{"id": 568, "chinese": "选择", "pinyin": "xuǎn zé", "portuguese": "escolher/selecionar", "categorias": ["verbo"]},
{"id": 569, "chinese": "解决", "pinyin": "jiě jué", "portuguese": "resolver", "categorias": ["verbo"]},
{"id": 570, "chinese": "解释", "pinyin": "jiě shì", "portuguese": "explicar", "categorias": ["verbo"]},
{"id": 571, "chinese": "相信", "pinyin": "xiāng xìn", "portuguese": "acreditar/confiar", "categorias": ["verbo"]},
{"id": 572, "chinese": "明白", "pinyin": "míng bai", "portuguese": "entender/compreender", "categorias": ["verbo"]},
{"id": 573, "chinese": "记得", "pinyin": "jì de", "portuguese": "lembrar", "categorias": ["verbo"]},
{"id": 574, "chinese": "忘记", "pinyin": "wàng jì", "portuguese": "esquecer", "categorias": ["verbo"]},
{"id": 575, "chinese": "关心", "pinyin": "guān xīn", "portuguese": "preocupar-se/cuidar", "categorias": ["verbo"]},
{"id": 576, "chinese": "担心", "pinyin": "dān xīn", "portuguese": "preocupar-se", "categorias": ["verbo"]},
{"id": 577, "chinese": "害怕", "pinyin": "hài pà", "portuguese": "ter medo", "categorias": ["verbo"]},
{"id": 578, "chinese": "讨厌", "pinyin": "tǎo yàn", "portuguese": "odiar/detestar", "categorias": ["verbo"]},
{"id": 579, "chinese": "原谅", "pinyin": "yuán liàng", "portuguese": "perdoar", "categorias": ["verbo"]},
{"id": 580, "chinese": "尊重", "pinyin": "zūn zhòng", "portuguese": "respeitar", "categorias": ["verbo"]},
{"id": 581, "chinese": "感谢", "pinyin": "gǎn xiè", "portuguese": "agradecer", "categorias": ["verbo"]},
{"id": 582, "chinese": "欢迎", "pinyin": "huān yíng", "portuguese": "dar boas-vindas", "categorias": ["verbo"]},
{"id": 583, "chinese": "介绍", "pinyin": "jiè shào", "portuguese": "apresentar/introduzir", "categorias": ["verbo"]},
{"id": 584, "chinese": "比较", "pinyin": "bǐ jiào", "portuguese": "comparar/relativamente", "categorias": ["verbo", "advérbio"]},
{"id": 585, "chinese": "练习", "pinyin": "liàn xí", "portuguese": "praticar/exercitar", "categorias": ["verbo"]},
{"id": 586, "chinese": "考试", "pinyin": "kǎo shì", "portuguese": "prova/exame", "categorias": ["substantivo"]},
{"id": 587, "chinese": "作业", "pinyin": "zuò yè", "portuguese": "dever de casa/tarefa", "categorias": ["substantivo"]},
{"id": 588, "chinese": "成绩", "pinyin": "chéng jì", "portuguese": "nota/resultado escolar", "categorias": ["substantivo"]},
{"id": 589, "chinese": "毕业", "pinyin": "bì yè", "portuguese": "formar-se/graduar", "categorias": ["verbo"]},
{"id": 590, "chinese": "结婚", "pinyin": "jié hūn", "portuguese": "casar", "categorias": ["verbo"]},
{"id": 591, "chinese": "离婚", "pinyin": "lí hūn", "portuguese": "divorciar", "categorias": ["verbo"]},
{"id": 592, "chinese": "出生", "pinyin": "chū shēng", "portuguese": "nascer", "categorias": ["verbo"]},
{"id": 593, "chinese": "死", "pinyin": "sǐ", "portuguese": "morrer", "categorias": ["verbo"]},
{"id": 594, "chinese": "活", "pinyin": "huó", "portuguese": "viver/vivo", "categorias": ["verbo", "adjetivo"]},
{"id": 595, "chinese": "飞", "pinyin": "fēi", "portuguese": "voar", "categorias": ["verbo"]},
{"id": 596, "chinese": "爬", "pinyin": "pá", "portuguese": "escalar/engatinhar", "categorias": ["verbo"]},
{"id": 597, "chinese": "跳", "pinyin": "tiào", "portuguese": "pular/saltar", "categorias": ["verbo"]},
{"id": 598, "chinese": "踢", "pinyin": "tī", "portuguese": "chutar", "categorias": ["verbo"]},
{"id": 599, "chinese": "推", "pinyin": "tuī", "portuguese": "empurrar", "categorias": ["verbo"]},
{"id": 600, "chinese": "拉", "pinyin": "lā", "portuguese": "puxar", "categorias": ["verbo"]},
{"id": 601, "chinese": "搬", "pinyin": "bān", "portuguese": "mudar/carregar", "categorias": ["verbo"]},
{"id": 602, "chinese": "巴西", "pinyin": "bā xī", "portuguese": "Brasil", "categorias": ["nacionalidade", "lugar"]},
{"id": 603, "chinese": "巴西人", "pinyin": "bā xī rén", "portuguese": "brasileiro(a)", "categorias": ["nacionalidade", "substantivo"]},
{"id": 604, "chinese": "葡萄牙", "pinyin": "pú táo yá", "portuguese": "Portugal", "categorias": ["nacionalidade", "lugar"]},
{"id": 605, "chinese": "葡萄牙人", "pinyin": "pú táo yá rén", "portuguese": "português(a)", "categorias": ["nacionalidade", "substantivo"]},
{"id": 606, "chinese": "中国", "pinyin": "zhōng guó", "portuguese": "China", "categorias": ["nacionalidade", "lugar"]},
{"id": 607, "chinese": "中国人", "pinyin": "zhōng guó rén", "portuguese": "chinês(a)", "categorias": ["nacionalidade", "substantivo"]},
{"id": 608, "chinese": "美国", "pinyin": "měi guó", "portuguese": "Estados Unidos", "categorias": ["nacionalidade", "lugar"]},
{"id": 609, "chinese": "美国人", "pinyin": "měi guó rén", "portuguese": "americano(a)", "categorias": ["nacionalidade", "substantivo"]},
{"id": 610, "chinese": "日本", "pinyin": "rì běn", "portuguese": "Japão", "categorias": ["nacionalidade", "lugar"]},
{"id": 611, "chinese": "日本人", "pinyin": "rì běn rén", "portuguese": "japonês(a)", "categorias": ["nacionalidade", "substantivo"]},
{"id": 612, "chinese": "英国", "pinyin": "yīng guó", "portuguese": "Inglaterra/Reino Unido", "categorias": ["nacionalidade", "lugar"]},
{"id": 613, "chinese": "英国人", "pinyin": "yīng guó rén", "portuguese": "inglês(a)/britânico(a)", "categorias": ["nacionalidade", "substantivo"]},
{"id": 614, "chinese": "法国", "pinyin": "fǎ guó", "portuguese": "França", "categorias": ["nacionalidade", "lugar"]},
{"id": 615, "chinese": "法国人", "pinyin": "fǎ guó rén", "portuguese": "francês(a)", "categorias": ["nacionalidade", "substantivo"]},
{"id": 616, "chinese": "德国", "pinyin": "dé guó", "portuguese": "Alemanha", "categorias": ["nacionalidade", "lugar"]},
{"id": 617, "chinese": "德国人", "pinyin": "dé guó rén", "portuguese": "alemão(ã)", "categorias": ["nacionalidade", "substantivo"]},
{"id": 618, "chinese": "意大利", "pinyin": "yì dà lì", "portuguese": "Itália", "categorias": ["nacionalidade", "lugar"]},
{"id": 619, "chinese": "意大利人", "pinyin": "yì dà lì rén", "portuguese": "italiano(a)", "categorias": ["nacionalidade", "substantivo"]},
{"id": 620, "chinese": "西班牙", "pinyin": "xī bān yá", "portuguese": "Espanha", "categorias": ["nacionalidade", "lugar"]},
{"id": 621, "chinese": "西班牙人", "pinyin": "xī bān yá rén", "portuguese": "espanhol(a)", "categorias": ["nacionalidade", "substantivo"]},
{"id": 622, "chinese": "俄罗斯", "pinyin": "é luó sī", "portuguese": "Rússia", "categorias": ["nacionalidade", "lugar"]},
{"id": 623, "chinese": "俄罗斯人", "pinyin": "é luó sī rén", "portuguese": "russo(a)", "categorias": ["nacionalidade", "substantivo"]},
{"id": 624, "chinese": "韩国", "pinyin": "hán guó", "portuguese": "Coreia do Sul", "categorias": ["nacionalidade", "lugar"]},
{"id": 625, "chinese": "韩国人", "pinyin": "hán guó rén", "portuguese": "sul-coreano(a)", "categorias": ["nacionalidade", "substantivo"]}

]